teciolib/2017r2_tecio_so.py
teciolib/2017r3_tecio_dll.py
teciolib/__init__.py
teciolib/bin2017r2_tecio_so.py
teciolib/bin2017r3_tecio_dll.py
tecio_lib-1.0.dist-info/METADATA
tecio_lib-1.0.dist-info/WHEEL
tecio_lib-1.0.dist-info/top_level.txt
tecio_lib-1.0.dist-info/RECORD
