Metadata-Version: 2.1
Name: tecio-lib
Version: 1.0
Summary: My pypi module
Home-page: https://github.com/blacksong
Author: Blacksong
Author-email: blacksong@yeah.net
License: UNKNOWN
Platform: python 3
Classifier: Programming Language :: Python :: 3
Classifier: Operating System :: OS Independent
Classifier: Topic :: Software Development :: Libraries :: Python Modules
